detecting/__init__.py
detecting/build/__init__.py
detecting/build/fasterrcnn.py
detecting/config/__init__.py
detecting/config/defaults.py
detecting/datasets/__init__.py
detecting/datasets/coco.py
detecting/datasets/data_generator.py
detecting/datasets/datasets.py
detecting/datasets/mydata.py
detecting/datasets/transforms.py
detecting/datasets/utils.py
detecting/datasets/voc.py
detecting/loss/__init__.py
detecting/loss/losses.py
detecting/models/__init__.py
detecting/models/anchors/__init__.py
detecting/models/anchors/anchor_generator.py
detecting/models/anchors/anchor_target.py
detecting/models/backbones/__init__.py
detecting/models/backbones/get_backbone.py
detecting/models/backbones/resnet_v1.py
detecting/models/bbox_heads/__init__.py
detecting/models/bbox_heads/bbox_head.py
detecting/models/bbox_heads/bbox_target.py
detecting/models/detectors/__init__.py
detecting/models/detectors/faster_rcnn.py
detecting/models/roi_extractors/__init__.py
detecting/models/roi_extractors/roi_align.py
detecting/models/rpn_heads/__init__.py
detecting/models/rpn_heads/rpn_head.py
detecting/solver/__init__.py
detecting/solver/lr_schedules.py
detecting/solver/optimizer.py
detecting/utils/__init__.py
detecting/utils/colors.py
detecting/utils/compute_map.py
detecting/utils/eval_coco.py
detecting/utils/iou.py
detecting/utils/logger.py
detecting/utils/misc.py
detecting/utils/model_util.py
detecting/utils/transforms.py
detecting/utils/visualize.py
detecting-0.20.dist-info/LICENSE
detecting-0.20.dist-info/METADATA
detecting-0.20.dist-info/WHEEL
detecting-0.20.dist-info/top_level.txt
detecting-0.20.dist-info/RECORD
