Metadata-Version: 2.1
Name: detecting
Version: 0.20
Summary: detecting
Home-page: https://github.com/Qinbf/detecting
Author: QinBingFeng
Author-email: 114479602@qq.com
License: MIT
Platform: UNKNOWN
Requires-Dist: numpy
Requires-Dist: matplotlib
Requires-Dist: opencv-python
Requires-Dist: h5py
Requires-Dist: yacs
Requires-Dist: tqdm
Provides-Extra: coco
Requires-Dist: pycocotools ; extra == 'coco'
